lab2/vsrc/bcd7seg.v
module bcd7seg(
  input  [3:0] b,
  output reg [6:0] h
);

always @(*) begin
  case (b)
    4'b0000: h = 7'b0000001; // 0
    4'b0001: h = 7'b1001111; // 1
    4'b0010: h = 7'b0010010; // 2
    4'b0011: h = 7'b0000110; // 3
    4'b0100: h = 7'b1001100; // 4
    4'b0101: h = 7'b0100100; // 5
    4'b0110: h = 7'b0100000; // 6
    4'b0111: h = 7'b0001111; // 7
    4'b1000: h = 7'b0000000; // 8
    4'b1001: h = 7'b0000100; // 9
    default: h = 7'b0000000; // off
  endcase
end
endmodule

lab2/vsrc/encode83.v
module encode83(x, en, y, indicate);
    input [7:0] x;
    input en;
    output reg [2:0] y;
    output reg indicate;

    always @(x, en) begin
        y = 3'b000;
        indicate = 1'b0;
        if (en) begin
            if (x != 0) begin
            indicate = 1'b1;
            for (int i = 0; i < 8; i++) 
                if (x[i]) y = i[2:0];
            end
            else indicate = 1'b0;
        end
    end
endmodule

lab2/vsrc/top.v
module top(x, en, led, indicate, seg);
    input [7:0] x;
    input en;
    output reg [2:0] led;
    output reg indicate;
    output reg [6:0] seg;

    encode83 encode83_inst (
        .x(x),
        .en(en),
        .y(led),
        .indicate(indicate)
    );

    bcd7seg bcd7seg_inst (
        .b({1'b0,led}),
        .h(seg)
    );
endmodule

lab2/dump.vcd
$version Generated by VerilatedVcd $end
$timescale 1s $end
 $scope module TOP $end
  $var wire 8 # x [7:0] $end
  $var wire 1 $ en $end
  $var wire 3 % led [2:0] $end
  $var wire 1 & indicate $end
  $var wire 7 ' seg [6:0] $end
  $scope module top $end
   $var wire 8 # x [7:0] $end
   $var wire 1 $ en $end
   $var wire 3 % led [2:0] $end
   $var wire 1 & indicate $end
   $var wire 7 ' seg [6:0] $end
   $scope module bcd7seg_inst $end
    $var wire 4 ( b [3:0] $end
    $var wire 7 ' h [6:0] $end
   $upscope $end
   $scope module encode83_inst $end
    $var wire 8 # x [7:0] $end
    $var wire 1 $ en $end
    $var wire 3 % y [2:0] $end
    $var wire 1 & indicate $end
    $scope module unnamedblk1 $end
     $var wire 32 ) i [31:0] $end
    $upscope $end
   $upscope $end
  $upscope $end
 $upscope $end
$enddefinitions $end


#1
b00000000 #
1$
b000 %
0&
b0000001 '
b0000 (
b00000000000000000000000000000000 )
#2
b00000001 #
1&
b00000000000000000000000000001000 )
#3
b00000010 #
b001 %
b1001111 '
b0001 (
#4
b00000100 #
b010 %
b0010010 '
b0010 (
#5
b00001000 #
b011 %
b0000110 '
b0011 (
#6
b00010000 #
b100 %
b1001100 '
b0100 (
#7
b00100000 #
b101 %
b0100100 '
b0101 (
#8
b01000000 #
b110 %
b0100000 '
b0110 (
#9
b10000000 #
b111 %
b0001111 '
b0111 (
