lab3/vsrc/alu.v
module alu(
    input [3:0] a,
    input [3:0] b,
    input [2:0] op,
    output reg [3:0] result,
    output reg cf,
    output reg zf,
    output reg of
);
    reg [3:0] temp;
    always @(*) begin
        zf = 0;
        cf = 0;
        of = 0;
        result = 0;
        temp = 0;
        casez (op)
            3'b00z: begin // Add and Sub
                temp = b ^ {4{op[0]}};
                {cf, result} = a + temp + {3'b0,op[0]};
                of = (a[3] == temp[3]) && (result[3] != a[3]);
            end
            3'b010: begin // Not A
                result = ~a;
                cf = 0;
                of = 0;
            end
            3'b011: begin // And
                result = a & b;
                cf = 0;
                of = 0;
            end
            3'b100: begin // Or
                result = a | b;
                cf = 0;
                of = 0;
            end
            3'b101: begin // Xor
                result = a ^ b;
                cf = 0;
                of = 0;
            end
            3'b110: begin // Less than
                // a - b
                temp = b ^ 4'b1111;
                {cf, result} = a + temp + 1;
                of = (a[3] == temp[3]) && (result[3] != a[3]);
                // 7 - （-8）
                // 0111 - 1000
                // temp = 0111
                if (of) result = a[3] ? 1 : 0; // a is negative, result is 1 if a < b
                else result = (result == 0) ? 0:{3'b0, result[3]};
            end
            3'b111: begin // Equal
                result = (a == b) ? 1 : 0;
                cf = 0;
                of = 0;
            end
            default: begin // Nop
                result = 0;
                cf = 0;
                of = 0;
                zf = 0;
            end
        endcase
        zf = ~(| result);
    end
endmodule

lab3/dump.vcd
$version Generated by VerilatedVcd $end
$timescale 1s $end
 $scope module TOP $end
  $var wire 4 # a [3:0] $end
  $var wire 4 $ b [3:0] $end
  $var wire 3 % op [2:0] $end
  $var wire 4 & result [3:0] $end
  $var wire 1 ' cf $end
  $var wire 1 ( zf $end
  $var wire 1 ) of $end
  $scope module alu $end
   $var wire 4 # a [3:0] $end
   $var wire 4 $ b [3:0] $end
   $var wire 3 % op [2:0] $end
   $var wire 4 & result [3:0] $end
   $var wire 1 ' cf $end
   $var wire 1 ( zf $end
   $var wire 1 ) of $end
   $var wire 4 * temp [3:0] $end
  $upscope $end
 $upscope $end
$enddefinitions $end


#1
b0000 #
b0000 $
b000 %
b0000 &
0'
1(
0)
b0000 *
#2
b0001 #
b0010 $
b0011 &
0(
b0010 *
#3
b0101 #
b0111 &
#4
b0101 $
b1010 &
1)
b0101 *
#5
b1111 #
b0001 $
b0000 &
1'
1(
0)
b0001 *
#6
b1110 #
b1101 $
b1011 &
0(
b1101 *
#7
b1011 #
b1011 $
b0110 &
1)
b1011 *
#8
b0111 #
b0001 $
b1000 &
0'
b0001 *
#9
b1001 #
b1110 $
b0111 &
1'
b1110 *
#10
b0000 #
b0000 $
b001 %
b0000 &
1(
0)
b1111 *
#11
b0101 #
b0010 $
b0011 &
0(
b1101 *
#12
b0010 #
b0101 $
b1101 &
0'
b1010 *
#13
b1111 #
b0001 $
b1110 &
1'
b1110 *
#14
b0001 #
b1111 $
b0010 &
0'
b0000 *
#15
b0101 #
b1011 $
b1010 &
1)
b0100 *
#16
b1011 #
b0101 $
b0110 &
1'
b1010 *
#17
b0111 #
b1001 $
b1110 &
0'
b0110 *
#18
b1000 #
b0001 $
b0111 &
1'
b1110 *
#19
b0000 #
b0000 $
b010 %
b1111 &
0'
0)
b0000 *
#20
b1111 #
b0000 &
1(
#21
b0101 #
b1010 &
0(
#22
b1010 #
b0101 &
#23
b0000 #
b1111 $
b011 %
b0000 &
1(
#24
b1111 #
b0001 $
b0001 &
0(
#25
b1010 #
b0101 $
b0000 &
1(
#26
b1100 #
b0110 $
b0100 &
0(
#27
b0000 #
b0000 $
b100 %
b0000 &
1(
#28
b0001 #
b0010 $
b0011 &
0(
#29
b1010 #
b0101 $
b1111 &
#30
b1100 #
b0011 $
#31
b0000 #
b0000 $
b101 %
b0000 &
1(
#32
b1111 #
b1111 $
#33
b1010 #
b0101 $
b1111 &
0(
#34
b1100 #
b0110 $
b1010 &
#35
b0001 #
b0010 $
b110 %
b0001 &
b1101 *
#36
b0101 #
b0000 &
1'
1(
#37
b1111 #
b0001 $
b0001 &
0(
b1110 *
#38
b0001 #
b1111 $
b0000 &
0'
1(
b0000 *
#39
b1000 #
b0001 $
b0001 &
1'
0(
1)
b1110 *
#40
b0111 #
b1000 $
b0000 &
0'
1(
b0111 *
#41
b0010 #
b0010 $
1'
0)
b1101 *
#42
b1111 #
b1111 $
b0000 *
#43
b0111 #
b1000 $
0'
1)
b0111 *
#44
b1000 #
b0111 $
b0001 &
1'
0(
b1000 *
#45
b0101 #
b0101 $
b111 %
0'
0)
b0000 *
#46
b0011 $
b0000 &
1(
#47
b1111 #
b1111 $
b0001 &
0(
#48
b0000 #
b0000 $
